{
  "date": "Monday, February 16, 2026",
  "prices": {
    "gold": 5041.8,
    "silver": 77.41,
    "btc": 69455.0,
    "eth": 2048.45
  },
  "news": [
    {
      "title": "David Hunter: 'Start Buying Gold ASAP', Target $5,000 in 3-6 Months",
      "summary": "Contrarian macro strategist David Hunter urges immediate accumulation of gold, predicting a final 'melt-up' that could push prices to $5,000 within the next quarter.",
      "url": "https://www.youtube.com/watch?v=mYrAxaJy_KQ"
    },
    {
      "title": "Kalshi Ends Polymarket Dominance with 60% Share",
      "summary": "The prediction market landscape has shifted drastically; regulated exchange Kalshi now captures 60% of market share as institutional volumes surge.",
      "url": "https://www.financemagnates.com/forex/analysis/kalshi-captures-60-market-share-ending-polymarkets-prediction-market-dominance/"
    },
    {
      "title": "ICE Launches 'Polymarket Signals' for Wall Street Institutions",
      "summary": "Intercontinental Exchange (ICE) has launched a dedicated sentiment tool for professional investors, legitimizing prediction market data as a core signal for traditional finance.",
      "url": "https://www.financemagnates.com/institutional-forex/ice-is-turning-prediction-market-odds-into-signals-and-sentiment-tools-for-wall-street/"
    }
  ],
  "institutional": {
    "macro": {
      "firm": "ICE",
      "analyst": "Institutional Tooling",
      "insight": "Normalized prediction market data is now being integrated into institutional workflows to capture real-time sentiment shifts.",
      "url": "https://www.financemagnates.com/institutional-forex/ice-is-turning-prediction-market-odds-into-signals-and-sentiment-tools-for-wall-street/"
    },
    "metals": [
      {
        "firm": "Futu News",
        "analyst": "Institutional Views",
        "insight": "Institutions remain long-term bullish on gold despite short-term volatility, validating the rebound as a key entry point.",
        "url": "https://news.futunn.com/en/post/68603071/gold-and-silver-prices-rebound-institutions-are-bullish-on-long"
      }
    ],
    "crypto": {
      "firm": "Kaito & Polymarket",
      "analyst": "Verifiable Intelligence",
      "insight": "The launch of verifiable social intelligence tools marks a shift toward transparency in tracking crypto social sentiment.",
      "url": "https://cryptorank.io/news/feed/63c94-prediction-markets-polymarket-partner-kaito"
    }
  },
  "social_intelligence": [
    {
      "source": "X (Twitter)",
      "asset": "Bitcoin",
      "signal": "Neutral",
      "insight": "Traders are debating if $70k is a local top, with some eyeing a $55k bottom retest.",
      "confidence": "65%"
    },
    {
      "source": "X (Twitter)",
      "asset": "Ethereum",
      "signal": "Bullish",
      "insight": "Traders are highlighting a TD buy signal on the daily chart, sparking optimism for a trend reversal.",
      "confidence": "80%"
    },
    {
      "source": "X (Twitter)",
      "asset": "Gold",
      "signal": "Bullish",
      "insight": "Gold's firm hold above the $5,000 psychological level is fueling a strong retail consensus for a breakout toward $5,600.",
      "confidence": "90%"
    },
    {
      "source": "X (Twitter)",
      "asset": "Silver",
      "signal": "Bullish",
      "insight": "Retail traders are focused on a massive $17/oz East-West arbitrage gap and COMEX options expiration as catalysts for an $80+ target.",
      "confidence": "85%"
    }
  ],
  "predictions": [
    {
      "label": "GOLD PRICE",
      "title": "What will Gold (GC) hit__ by end of February?",
      "url": "https://polymarket.com/event/what-will-gold-gc-hit-by-end-of-february",
      "nominal": "$5,982,568",
      "outcomes": [
        {
          "name": "\u2191 $6,000",
          "prob": 0.013,
          "vol": 562408.890242,
          "vol_fmt": "$562,408",
          "price_val": 6000.0,
          "prob_pct": "1%"
        },
        {
          "name": "\u2191 $5,800",
          "prob": 0.0335,
          "vol": 326915.061152,
          "vol_fmt": "$326,915",
          "price_val": 5800.0,
          "prob_pct": "3%"
        },
        {
          "name": "\u2191 $5,500",
          "prob": 0.1355,
          "vol": 786326.925035,
          "vol_fmt": "$786,326",
          "price_val": 5500.0,
          "prob_pct": "13%"
        },
        {
          "name": "\u2193 $4,600",
          "prob": 0.157,
          "vol": 215871.212472,
          "vol_fmt": "$215,871",
          "price_val": 4600.0,
          "prob_pct": "15%"
        },
        {
          "name": "\u2193 $4,450",
          "prob": 0.048,
          "vol": 141692.986004,
          "vol_fmt": "$141,692",
          "price_val": 4450.0,
          "prob_pct": "4%"
        },
        {
          "name": "\u2193 $4,200",
          "prob": 0.0155,
          "vol": 140382.877183,
          "vol_fmt": "$140,382",
          "price_val": 4200.0,
          "prob_pct": "1%"
        }
      ],
      "color": "yellow"
    },
    {
      "label": "SILVER PRICE",
      "title": "Will Silver (SI) hit__ by end of February?",
      "url": "https://polymarket.com/event/will-silver-si-hit-by-end-of-february",
      "nominal": "$3,960,735",
      "outcomes": [
        {
          "name": "\u2191 $150",
          "prob": 0.0105,
          "vol": 202027.656813,
          "vol_fmt": "$202,027",
          "price_val": 150.0,
          "prob_pct": "1%"
        },
        {
          "name": "\u2191 $140",
          "prob": 0.011,
          "vol": 235077.365322,
          "vol_fmt": "$235,077",
          "price_val": 140.0,
          "prob_pct": "1%"
        },
        {
          "name": "\u2191 $130",
          "prob": 0.015,
          "vol": 264723.817382,
          "vol_fmt": "$264,723",
          "price_val": 130.0,
          "prob_pct": "1%"
        },
        {
          "name": "\u2191 $120",
          "prob": 0.0425,
          "vol": 509928.043352,
          "vol_fmt": "$509,928",
          "price_val": 120.0,
          "prob_pct": "4%"
        },
        {
          "name": "\u2193 $75",
          "prob": 0.692,
          "vol": 378872.458755,
          "vol_fmt": "$378,872",
          "price_val": 75.0,
          "prob_pct": "69%"
        },
        {
          "name": "\u2193 $70",
          "prob": 0.385,
          "vol": 129652.433601,
          "vol_fmt": "$129,652",
          "price_val": 70.0,
          "prob_pct": "38%"
        }
      ],
      "color": "gray"
    },
    {
      "label": "BTC PRICE",
      "title": "What price will Bitcoin hit in February?",
      "url": "https://polymarket.com/event/what-price-will-bitcoin-hit-in-february-2026",
      "nominal": "$64,073,772",
      "outcomes": [
        {
          "name": "\u2191 95,000",
          "prob": 0.0105,
          "vol": 2520223.220565,
          "vol_fmt": "$2,520,223",
          "price_val": 95000.0,
          "prob_pct": "1%"
        },
        {
          "name": "\u2191 90,000",
          "prob": 0.0195,
          "vol": 3411606.649397,
          "vol_fmt": "$3,411,606",
          "price_val": 90000.0,
          "prob_pct": "1%"
        },
        {
          "name": "\u2191 85,000",
          "prob": 0.0445,
          "vol": 4278086.382596,
          "vol_fmt": "$4,278,086",
          "price_val": 85000.0,
          "prob_pct": "4%"
        },
        {
          "name": "\u2191 80,000",
          "prob": 0.115,
          "vol": 1242475.639189,
          "vol_fmt": "$1,242,475",
          "price_val": 80000.0,
          "prob_pct": "11%"
        },
        {
          "name": "\u2191 75,000",
          "prob": 0.36,
          "vol": 1599709.017508,
          "vol_fmt": "$1,599,709",
          "price_val": 75000.0,
          "prob_pct": "36%"
        },
        {
          "name": "\u2193 60,000",
          "prob": 0.25,
          "vol": 1240946.138484,
          "vol_fmt": "$1,240,946",
          "price_val": 60000.0,
          "prob_pct": "25%"
        }
      ],
      "color": "purple"
    },
    {
      "label": "ETH PRICE",
      "title": "What price will Ethereum hit in February?",
      "url": "https://polymarket.com/event/what-price-will-ethereum-hit-in-february-2026",
      "nominal": "$21,123,614",
      "outcomes": [
        {
          "name": "\u2191 3,000",
          "prob": 0.016,
          "vol": 592123.470307,
          "vol_fmt": "$592,123",
          "price_val": 3000.0,
          "prob_pct": "1%"
        },
        {
          "name": "\u2191 2,800",
          "prob": 0.0245,
          "vol": 1227888.577921,
          "vol_fmt": "$1,227,888",
          "price_val": 2800.0,
          "prob_pct": "2%"
        },
        {
          "name": "\u2193 1,600",
          "prob": 0.232,
          "vol": 1084019.064888,
          "vol_fmt": "$1,084,019",
          "price_val": 1600.0,
          "prob_pct": "23%"
        },
        {
          "name": "\u2193 1,400",
          "prob": 0.0805,
          "vol": 707984.091479,
          "vol_fmt": "$707,984",
          "price_val": 1400.0,
          "prob_pct": "8%"
        },
        {
          "name": "\u2193 1,200",
          "prob": 0.0195,
          "vol": 1122183.218489,
          "vol_fmt": "$1,122,183",
          "price_val": 1200.0,
          "prob_pct": "1%"
        }
      ],
      "color": "blue"
    },
    {
      "label": "MACRO / FED",
      "title": "Who will Trump nominate as Fed Chair?",
      "url": "https://polymarket.com/event/who-will-trump-nominate-as-fed-chair",
      "nominal": "$482,274,772",
      "outcomes": [
        {
          "name": "Kevin Warsh",
          "prob": 0.9555,
          "vol": 39348790.395903,
          "vol_fmt": "$39,348,790",
          "price_val": 0,
          "prob_pct": "89%"
        },
        {
          "name": "Rick Rieder",
          "prob": 0.075,
          "vol": 0.0,
          "vol_fmt": "$0",
          "price_val": 0,
          "prob_pct": "7%"
        },
        {
          "name": "James Bullard",
          "prob": 0.038,
          "vol": 5005.309568,
          "vol_fmt": "$5,005",
          "price_val": 0,
          "prob_pct": "3%"
        }
      ],
      "color": "blue"
    },
    {
      "label": "GEOPOLITICS",
      "title": "US strikes Iran by...?",
      "url": "https://polymarket.com/event/us-strikes-iran-by",
      "nominal": "$260,291,057",
      "outcomes": [
        {
          "name": "June 30",
          "prob": 0.455,
          "vol": 5168065.232627,
          "vol_fmt": "$5,168,065",
          "price_val": 0,
          "prob_pct": "44%"
        },
        {
          "name": "March 31",
          "prob": 0.325,
          "vol": 9019774.992484,
          "vol_fmt": "$9,019,774",
          "price_val": 0,
          "prob_pct": "32%"
        },
        {
          "name": "March 15",
          "prob": 0.235,
          "vol": 236603.693808,
          "vol_fmt": "$236,603",
          "price_val": 0,
          "prob_pct": "23%"
        }
      ],
      "color": "red"
    },
    {
      "label": "WILDCARD",
      "title": "Fed decision in March?",
      "url": "https://polymarket.com/event/fed-decision-in-march-885",
      "nominal": "$120,293,913",
      "outcomes": [
        {
          "name": "No change",
          "prob": 0.925,
          "vol": 15018739.818666,
          "vol_fmt": "$15,018,739",
          "price_val": 0,
          "prob_pct": "92%"
        },
        {
          "name": "25 bps decrease",
          "prob": 0.065,
          "vol": 15642722.194986,
          "vol_fmt": "$15,642,722",
          "price_val": 0,
          "prob_pct": "6%"
        },
        {
          "name": "50+ bps decrease",
          "prob": 0.0065,
          "vol": 47378472.603257,
          "vol_fmt": "$47,378,472",
          "price_val": 0,
          "prob_pct": "0%"
        }
      ],
      "color": "green"
    }
  ]
}